<?xml version="1.0" encoding="utf-8"?>
<NodeSet xmlns:i="http://www.w3.org/2001/XMLSchema-instance" xmlns="http://opcfoundation.org/UA/2008/02/Types.xsd">
  <NamespaceUris>
    <String>http://opcfoundation.org/UA/</String>
    <String>http://PLCopen.org/OpcUa/IEC61131-3/</String>
    <String>http://opcfoundation.org/UA/DI/</String>
  </NamespaceUris>
  <ServerUris />
  <Nodes>
    <Node i:type="ObjectTypeNode">
      <NodeId>
        <Identifier>ns=1;i=1001</Identifier>
      </NodeId>
      <NodeClass>ObjectType_8</NodeClass>
      <BrowseName>
        <NamespaceIndex>1</NamespaceIndex>
        <Name>CtrlConfigurationType</Name>
      </BrowseName>
      <DisplayName>
        <Locale></Locale>
        <Text>CtrlConfigurationType</Text>
      </DisplayName>
      <Description i:nil="true" />
      <WriteMask>0</WriteMask>
      <UserWriteMask>0</UserWriteMask>
      <References>
        <ReferenceNode>
          <ReferenceTypeId>
            <Identifier>i=45</Identifier>
          </ReferenceTypeId>
          <IsInverse>true</IsInverse>
          <TargetId>
            <Identifier>ns=2;i=1002</Identifier>
          </TargetId>
        </ReferenceNode>
        <ReferenceNode>
          <ReferenceTypeId>
            <Identifier>i=47</Identifier>
          </ReferenceTypeId>
          <IsInverse>false</IsInverse>
          <TargetId>
            <Identifier>ns=1;i=5002</Identifier>
          </TargetId>
        </ReferenceNode>
        <ReferenceNode>
          <ReferenceTypeId>
            <Identifier>i=47</Identifier>
          </ReferenceTypeId>
          <IsInverse>false</IsInverse>
          <TargetId>
            <Identifier>ns=1;i=5004</Identifier>
          </TargetId>
        </ReferenceNode>
        <ReferenceNode>
          <ReferenceTypeId>
            <Identifier>i=47</Identifier>
          </ReferenceTypeId>
          <IsInverse>false</IsInverse>
          <TargetId>
            <Identifier>ns=1;i=5006</Identifier>
          </TargetId>
        </ReferenceNode>
        <ReferenceNode>
          <ReferenceTypeId>
            <Identifier>i=47</Identifier>
          </ReferenceTypeId>
          <IsInverse>false</IsInverse>
          <TargetId>
            <Identifier>ns=1;i=5007</Identifier>
          </TargetId>
        </ReferenceNode>
        <ReferenceNode>
          <ReferenceTypeId>
            <Identifier>i=47</Identifier>
          </ReferenceTypeId>
          <IsInverse>false</IsInverse>
          <TargetId>
            <Identifier>ns=1;i=5008</Identifier>
          </TargetId>
        </ReferenceNode>
        <ReferenceNode>
          <ReferenceTypeId>
            <Identifier>i=47</Identifier>
          </ReferenceTypeId>
          <IsInverse>false</IsInverse>
          <TargetId>
            <Identifier>ns=1;i=5009</Identifier>
          </TargetId>
        </ReferenceNode>
        <ReferenceNode>
          <ReferenceTypeId>
            <Identifier>i=47</Identifier>
          </ReferenceTypeId>
          <IsInverse>false</IsInverse>
          <TargetId>
            <Identifier>ns=1;i=5010</Identifier>
          </TargetId>
        </ReferenceNode>
      </References>
      <IsAbstract>false</IsAbstract>
    </Node>
    <Node i:type="ObjectTypeNode">
      <NodeId>
        <Identifier>ns=1;i=1002</Identifier>
      </NodeId>
      <NodeClass>ObjectType_8</NodeClass>
      <BrowseName>
        <NamespaceIndex>1</NamespaceIndex>
        <Name>CtrlResourceType</Name>
      </BrowseName>
      <DisplayName>
        <Locale></Locale>
        <Text>CtrlResourceType</Text>
      </DisplayName>
      <Description i:nil="true" />
      <WriteMask>0</WriteMask>
      <UserWriteMask>0</UserWriteMask>
      <References>
        <ReferenceNode>
          <ReferenceTypeId>
            <Identifier>i=45</Identifier>
          </ReferenceTypeId>
          <IsInverse>true</IsInverse>
          <TargetId>
            <Identifier>ns=2;i=1002</Identifier>
          </TargetId>
        </ReferenceNode>
        <ReferenceNode>
          <ReferenceTypeId>
            <Identifier>i=47</Identifier>
          </ReferenceTypeId>
          <IsInverse>false</IsInverse>
          <TargetId>
            <Identifier>ns=1;i=5012</Identifier>
          </TargetId>
        </ReferenceNode>
        <ReferenceNode>
          <ReferenceTypeId>
            <Identifier>i=47</Identifier>
          </ReferenceTypeId>
          <IsInverse>false</IsInverse>
          <TargetId>
            <Identifier>ns=1;i=5014</Identifier>
          </TargetId>
        </ReferenceNode>
        <ReferenceNode>
          <ReferenceTypeId>
            <Identifier>i=47</Identifier>
          </ReferenceTypeId>
          <IsInverse>false</IsInverse>
          <TargetId>
            <Identifier>ns=1;i=5016</Identifier>
          </TargetId>
        </ReferenceNode>
        <ReferenceNode>
          <ReferenceTypeId>
            <Identifier>i=47</Identifier>
          </ReferenceTypeId>
          <IsInverse>false</IsInverse>
          <TargetId>
            <Identifier>ns=1;i=5018</Identifier>
          </TargetId>
        </ReferenceNode>
        <ReferenceNode>
          <ReferenceTypeId>
            <Identifier>i=47</Identifier>
          </ReferenceTypeId>
          <IsInverse>false</IsInverse>
          <TargetId>
            <Identifier>ns=1;i=5019</Identifier>
          </TargetId>
        </ReferenceNode>
        <ReferenceNode>
          <ReferenceTypeId>
            <Identifier>i=47</Identifier>
          </ReferenceTypeId>
          <IsInverse>false</IsInverse>
          <TargetId>
            <Identifier>ns=1;i=5020</Identifier>
          </TargetId>
        </ReferenceNode>
      </References>
      <IsAbstract>false</IsAbstract>
    </Node>
    <Node i:type="ObjectTypeNode">
      <NodeId>
        <Identifier>ns=1;i=1003</Identifier>
      </NodeId>
      <NodeClass>ObjectType_8</NodeClass>
      <BrowseName>
        <NamespaceIndex>1</NamespaceIndex>
        <Name>CtrlProgramOrganizationUnitType</Name>
      </BrowseName>
      <DisplayName>
        <Locale></Locale>
        <Text>CtrlProgramOrganizationUnitType</Text>
      </DisplayName>
      <Description i:nil="true" />
      <WriteMask>0</WriteMask>
      <UserWriteMask>0</UserWriteMask>
      <References>
        <ReferenceNode>
          <ReferenceTypeId>
            <Identifier>i=45</Identifier>
          </ReferenceTypeId>
          <IsInverse>true</IsInverse>
          <TargetId>
            <Identifier>ns=2;i=1003</Identifier>
          </TargetId>
        </ReferenceNode>
        <ReferenceNode>
          <ReferenceTypeId>
            <Identifier>i=47</Identifier>
          </ReferenceTypeId>
          <IsInverse>false</IsInverse>
          <TargetId>
            <Identifier>ns=1;i=6001</Identifier>
          </TargetId>
        </ReferenceNode>
        <ReferenceNode>
          <ReferenceTypeId>
            <Identifier>i=45</Identifier>
          </ReferenceTypeId>
          <IsInverse>false</IsInverse>
          <TargetId>
            <Identifier>ns=1;i=1004</Identifier>
          </TargetId>
        </ReferenceNode>
        <ReferenceNode>
          <ReferenceTypeId>
            <Identifier>i=45</Identifier>
          </ReferenceTypeId>
          <IsInverse>false</IsInverse>
          <TargetId>
            <Identifier>ns=1;i=1005</Identifier>
          </TargetId>
        </ReferenceNode>
      </References>
      <IsAbstract>true</IsAbstract>
    </Node>
    <Node i:type="ObjectTypeNode">
      <NodeId>
        <Identifier>ns=1;i=1004</Identifier>
      </NodeId>
      <NodeClass>ObjectType_8</NodeClass>
      <BrowseName>
        <NamespaceIndex>1</NamespaceIndex>
        <Name>CtrlProgramType</Name>
      </BrowseName>
      <DisplayName>
        <Locale></Locale>
        <Text>CtrlProgramType</Text>
      </DisplayName>
      <Description i:nil="true" />
      <WriteMask>0</WriteMask>
      <UserWriteMask>0</UserWriteMask>
      <References>
        <ReferenceNode>
          <ReferenceTypeId>
            <Identifier>i=45</Identifier>
          </ReferenceTypeId>
          <IsInverse>true</IsInverse>
          <TargetId>
            <Identifier>ns=1;i=1003</Identifier>
          </TargetId>
        </ReferenceNode>
        <ReferenceNode>
          <ReferenceTypeId>
            <Identifier>i=47</Identifier>
          </ReferenceTypeId>
          <IsInverse>false</IsInverse>
          <TargetId>
            <Identifier>ns=1;i=6002</Identifier>
          </TargetId>
        </ReferenceNode>
      </References>
      <IsAbstract>true</IsAbstract>
    </Node>
    <Node i:type="ObjectTypeNode">
      <NodeId>
        <Identifier>ns=1;i=1005</Identifier>
      </NodeId>
      <NodeClass>ObjectType_8</NodeClass>
      <BrowseName>
        <NamespaceIndex>1</NamespaceIndex>
        <Name>CtrlFunctionBlockType</Name>
      </BrowseName>
      <DisplayName>
        <Locale></Locale>
        <Text>CtrlFunctionBlockType</Text>
      </DisplayName>
      <Description i:nil="true" />
      <WriteMask>0</WriteMask>
      <UserWriteMask>0</UserWriteMask>
      <References>
        <ReferenceNode>
          <ReferenceTypeId>
            <Identifier>i=45</Identifier>
          </ReferenceTypeId>
          <IsInverse>true</IsInverse>
          <TargetId>
            <Identifier>ns=1;i=1003</Identifier>
          </TargetId>
        </ReferenceNode>
        <ReferenceNode>
          <ReferenceTypeId>
            <Identifier>i=47</Identifier>
          </ReferenceTypeId>
          <IsInverse>false</IsInverse>
          <TargetId>
            <Identifier>ns=1;i=6003</Identifier>
          </TargetId>
        </ReferenceNode>
      </References>
      <IsAbstract>true</IsAbstract>
    </Node>
    <Node i:type="ObjectTypeNode">
      <NodeId>
        <Identifier>ns=1;i=1006</Identifier>
      </NodeId>
      <NodeClass>ObjectType_8</NodeClass>
      <BrowseName>
        <NamespaceIndex>1</NamespaceIndex>
        <Name>CtrlTaskType</Name>
      </BrowseName>
      <DisplayName>
        <Locale></Locale>
        <Text>CtrlTaskType</Text>
      </DisplayName>
      <Description i:nil="true" />
      <WriteMask>0</WriteMask>
      <UserWriteMask>0</UserWriteMask>
      <References>
        <ReferenceNode>
          <ReferenceTypeId>
            <Identifier>i=45</Identifier>
          </ReferenceTypeId>
          <IsInverse>true</IsInverse>
          <TargetId>
            <Identifier>i=58</Identifier>
          </TargetId>
        </ReferenceNode>
        <ReferenceNode>
          <ReferenceTypeId>
            <Identifier>i=46</Identifier>
          </ReferenceTypeId>
          <IsInverse>false</IsInverse>
          <TargetId>
            <Identifier>ns=1;i=6004</Identifier>
          </TargetId>
        </ReferenceNode>
        <ReferenceNode>
          <ReferenceTypeId>
            <Identifier>i=46</Identifier>
          </ReferenceTypeId>
          <IsInverse>false</IsInverse>
          <TargetId>
            <Identifier>ns=1;i=6005</Identifier>
          </TargetId>
        </ReferenceNode>
        <ReferenceNode>
          <ReferenceTypeId>
            <Identifier>i=46</Identifier>
          </ReferenceTypeId>
          <IsInverse>false</IsInverse>
          <TargetId>
            <Identifier>ns=1;i=6006</Identifier>
          </TargetId>
        </ReferenceNode>
      </References>
      <IsAbstract>false</IsAbstract>
    </Node>
    <Node i:type="ObjectTypeNode">
      <NodeId>
        <Identifier>ns=1;i=1007</Identifier>
      </NodeId>
      <NodeClass>ObjectType_8</NodeClass>
      <BrowseName>
        <NamespaceIndex>1</NamespaceIndex>
        <Name>SFCType</Name>
      </BrowseName>
      <DisplayName>
        <Locale></Locale>
        <Text>SFCType</Text>
      </DisplayName>
      <Description i:nil="true" />
      <WriteMask>0</WriteMask>
      <UserWriteMask>0</UserWriteMask>
      <References>
        <ReferenceNode>
          <ReferenceTypeId>
            <Identifier>i=45</Identifier>
          </ReferenceTypeId>
          <IsInverse>true</IsInverse>
          <TargetId>
            <Identifier>i=58</Identifier>
          </TargetId>
        </ReferenceNode>
      </References>
      <IsAbstract>false</IsAbstract>
    </Node>
    <Node i:type="ReferenceTypeNode">
      <NodeId>
        <Identifier>ns=1;i=4001</Identifier>
      </NodeId>
      <NodeClass>ReferenceType_32</NodeClass>
      <BrowseName>
        <NamespaceIndex>1</NamespaceIndex>
        <Name>HasInputVars</Name>
      </BrowseName>
      <DisplayName>
        <Locale></Locale>
        <Text>HasInputVars</Text>
      </DisplayName>
      <Description i:nil="true" />
      <WriteMask>0</WriteMask>
      <UserWriteMask>0</UserWriteMask>
      <References>
        <ReferenceNode>
          <ReferenceTypeId>
            <Identifier>i=45</Identifier>
          </ReferenceTypeId>
          <IsInverse>true</IsInverse>
          <TargetId>
            <Identifier>i=47</Identifier>
          </TargetId>
        </ReferenceNode>
      </References>
      <IsAbstract>false</IsAbstract>
      <Symmetric>false</Symmetric>
      <InverseName>
        <Locale></Locale>
        <Text>InputVarsOf</Text>
      </InverseName>
    </Node>
    <Node i:type="ReferenceTypeNode">
      <NodeId>
        <Identifier>ns=1;i=4002</Identifier>
      </NodeId>
      <NodeClass>ReferenceType_32</NodeClass>
      <BrowseName>
        <NamespaceIndex>1</NamespaceIndex>
        <Name>HasOutputVars</Name>
      </BrowseName>
      <DisplayName>
        <Locale></Locale>
        <Text>HasOutputVars</Text>
      </DisplayName>
      <Description i:nil="true" />
      <WriteMask>0</WriteMask>
      <UserWriteMask>0</UserWriteMask>
      <References>
        <ReferenceNode>
          <ReferenceTypeId>
            <Identifier>i=45</Identifier>
          </ReferenceTypeId>
          <IsInverse>true</IsInverse>
          <TargetId>
            <Identifier>i=47</Identifier>
          </TargetId>
        </ReferenceNode>
      </References>
      <IsAbstract>false</IsAbstract>
      <Symmetric>false</Symmetric>
      <InverseName>
        <Locale></Locale>
        <Text>OutputVarsOf</Text>
      </InverseName>
    </Node>
    <Node i:type="ReferenceTypeNode">
      <NodeId>
        <Identifier>ns=1;i=4003</Identifier>
      </NodeId>
      <NodeClass>ReferenceType_32</NodeClass>
      <BrowseName>
        <NamespaceIndex>1</NamespaceIndex>
        <Name>HasInOutVars</Name>
      </BrowseName>
      <DisplayName>
        <Locale></Locale>
        <Text>HasInOutVars</Text>
      </DisplayName>
      <Description i:nil="true" />
      <WriteMask>0</WriteMask>
      <UserWriteMask>0</UserWriteMask>
      <References>
        <ReferenceNode>
          <ReferenceTypeId>
            <Identifier>i=45</Identifier>
          </ReferenceTypeId>
          <IsInverse>true</IsInverse>
          <TargetId>
            <Identifier>i=47</Identifier>
          </TargetId>
        </ReferenceNode>
      </References>
      <IsAbstract>false</IsAbstract>
      <Symmetric>false</Symmetric>
      <InverseName>
        <Locale></Locale>
        <Text>InOutVarsOf</Text>
      </InverseName>
    </Node>
    <Node i:type="ReferenceTypeNode">
      <NodeId>
        <Identifier>ns=1;i=4004</Identifier>
      </NodeId>
      <NodeClass>ReferenceType_32</NodeClass>
      <BrowseName>
        <NamespaceIndex>1</NamespaceIndex>
        <Name>HasLocalVars</Name>
      </BrowseName>
      <DisplayName>
        <Locale></Locale>
        <Text>HasLocalVars</Text>
      </DisplayName>
      <Description i:nil="true" />
      <WriteMask>0</WriteMask>
      <UserWriteMask>0</UserWriteMask>
      <References>
        <ReferenceNode>
          <ReferenceTypeId>
            <Identifier>i=45</Identifier>
          </ReferenceTypeId>
          <IsInverse>true</IsInverse>
          <TargetId>
            <Identifier>i=47</Identifier>
          </TargetId>
        </ReferenceNode>
      </References>
      <IsAbstract>false</IsAbstract>
      <Symmetric>false</Symmetric>
      <InverseName>
        <Locale></Locale>
        <Text>LocalVarsOf</Text>
      </InverseName>
    </Node>
    <Node i:type="ReferenceTypeNode">
      <NodeId>
        <Identifier>ns=1;i=4005</Identifier>
      </NodeId>
      <NodeClass>ReferenceType_32</NodeClass>
      <BrowseName>
        <NamespaceIndex>1</NamespaceIndex>
        <Name>HasExternalVars</Name>
      </BrowseName>
      <DisplayName>
        <Locale></Locale>
        <Text>HasExternalVars</Text>
      </DisplayName>
      <Description i:nil="true" />
      <WriteMask>0</WriteMask>
      <UserWriteMask>0</UserWriteMask>
      <References>
        <ReferenceNode>
          <ReferenceTypeId>
            <Identifier>i=45</Identifier>
          </ReferenceTypeId>
          <IsInverse>true</IsInverse>
          <TargetId>
            <Identifier>i=35</Identifier>
          </TargetId>
        </ReferenceNode>
      </References>
      <IsAbstract>false</IsAbstract>
      <Symmetric>false</Symmetric>
      <InverseName>
        <Locale></Locale>
        <Text>ExternalVarsOf</Text>
      </InverseName>
    </Node>
    <Node i:type="ReferenceTypeNode">
      <NodeId>
        <Identifier>ns=1;i=4006</Identifier>
      </NodeId>
      <NodeClass>ReferenceType_32</NodeClass>
      <BrowseName>
        <NamespaceIndex>1</NamespaceIndex>
        <Name>With</Name>
      </BrowseName>
      <DisplayName>
        <Locale></Locale>
        <Text>With</Text>
      </DisplayName>
      <Description i:nil="true" />
      <WriteMask>0</WriteMask>
      <UserWriteMask>0</UserWriteMask>
      <References>
        <ReferenceNode>
          <ReferenceTypeId>
            <Identifier>i=45</Identifier>
          </ReferenceTypeId>
          <IsInverse>true</IsInverse>
          <TargetId>
            <Identifier>i=32</Identifier>
          </TargetId>
        </ReferenceNode>
      </References>
      <IsAbstract>false</IsAbstract>
      <Symmetric>false</Symmetric>
      <InverseName>
        <Locale></Locale>
        <Text>Executes</Text>
      </InverseName>
    </Node>
    <Node i:type="ObjectNode">
      <NodeId>
        <Identifier>ns=1;i=5002</Identifier>
      </NodeId>
      <NodeClass>Object_1</NodeClass>
      <BrowseName>
        <NamespaceIndex>1</NamespaceIndex>
        <Name>MethodSet</Name>
      </BrowseName>
      <DisplayName>
        <Locale></Locale>
        <Text>MethodSet</Text>
      </DisplayName>
      <Description>
        <Locale></Locale>
        <Text>Flat list of Methods</Text>
      </Description>
      <WriteMask>0</WriteMask>
      <UserWriteMask>0</UserWriteMask>
      <References>
        <ReferenceNode>
          <ReferenceTypeId>
            <Identifier>i=47</Identifier>
          </ReferenceTypeId>
          <IsInverse>true</IsInverse>
          <TargetId>
            <Identifier>ns=1;i=1001</Identifier>
          </TargetId>
        </ReferenceNode>
        <ReferenceNode>
          <ReferenceTypeId>
            <Identifier>i=40</Identifier>
          </ReferenceTypeId>
          <IsInverse>false</IsInverse>
          <TargetId>
            <Identifier>i=58</Identifier>
          </TargetId>
        </ReferenceNode>
        <ReferenceNode>
          <ReferenceTypeId>
            <Identifier>i=37</Identifier>
          </ReferenceTypeId>
          <IsInverse>false</IsInverse>
          <TargetId>
            <Identifier>i=80</Identifier>
          </TargetId>
        </ReferenceNode>
        <ReferenceNode>
          <ReferenceTypeId>
            <Identifier>i=47</Identifier>
          </ReferenceTypeId>
          <IsInverse>false</IsInverse>
          <TargetId>
            <Identifier>ns=1;i=7001</Identifier>
          </TargetId>
        </ReferenceNode>
        <ReferenceNode>
          <ReferenceTypeId>
            <Identifier>i=47</Identifier>
          </ReferenceTypeId>
          <IsInverse>false</IsInverse>
          <TargetId>
            <Identifier>ns=1;i=7002</Identifier>
          </TargetId>
        </ReferenceNode>
      </References>
      <EventNotifier>0</EventNotifier>
    </Node>
    <Node i:type="ObjectNode">
      <NodeId>
        <Identifier>ns=1;i=5004</Identifier>
      </NodeId>
      <NodeClass>Object_1</NodeClass>
      <BrowseName>
        <NamespaceIndex>1</NamespaceIndex>
        <Name>Resources</Name>
      </BrowseName>
      <DisplayName>
        <Locale></Locale>
        <Text>Resources</Text>
      </DisplayName>
      <Description i:nil="true" />
      <WriteMask>0</WriteMask>
      <UserWriteMask>0</UserWriteMask>
      <References>
        <ReferenceNode>
          <ReferenceTypeId>
            <Identifier>i=47</Identifier>
          </ReferenceTypeId>
          <IsInverse>true</IsInverse>
          <TargetId>
            <Identifier>ns=1;i=1001</Identifier>
          </TargetId>
        </ReferenceNode>
        <ReferenceNode>
          <ReferenceTypeId>
            <Identifier>i=40</Identifier>
          </ReferenceTypeId>
          <IsInverse>false</IsInverse>
          <TargetId>
            <Identifier>ns=2;i=1004</Identifier>
          </TargetId>
        </ReferenceNode>
        <ReferenceNode>
          <ReferenceTypeId>
            <Identifier>i=37</Identifier>
          </ReferenceTypeId>
          <IsInverse>false</IsInverse>
          <TargetId>
            <Identifier>i=78</Identifier>
          </TargetId>
        </ReferenceNode>
        <ReferenceNode>
          <ReferenceTypeId>
            <Identifier>i=47</Identifier>
          </ReferenceTypeId>
          <IsInverse>false</IsInverse>
          <TargetId>
            <Identifier>ns=1;i=5005</Identifier>
          </TargetId>
        </ReferenceNode>
      </References>
      <EventNotifier>0</EventNotifier>
    </Node>
    <Node i:type="ObjectNode">
      <NodeId>
        <Identifier>ns=1;i=5005</Identifier>
      </NodeId>
      <NodeClass>Object_1</NodeClass>
      <BrowseName>
        <NamespaceIndex>2</NamespaceIndex>
        <Name>SupportedTypes</Name>
      </BrowseName>
      <DisplayName>
        <Locale></Locale>
        <Text>SupportedTypes</Text>
      </DisplayName>
      <Description>
        <Locale></Locale>
        <Text>Folder maintaining the set of (sub-types of) BaseObjectTypes that can be instantiated in the ConfigurableComponent</Text>
      </Description>
      <WriteMask>0</WriteMask>
      <UserWriteMask>0</UserWriteMask>
      <References>
        <ReferenceNode>
          <ReferenceTypeId>
            <Identifier>i=47</Identifier>
          </ReferenceTypeId>
          <IsInverse>true</IsInverse>
          <TargetId>
            <Identifier>ns=1;i=5004</Identifier>
          </TargetId>
        </ReferenceNode>
        <ReferenceNode>
          <ReferenceTypeId>
            <Identifier>i=40</Identifier>
          </ReferenceTypeId>
          <IsInverse>false</IsInverse>
          <TargetId>
            <Identifier>i=61</Identifier>
          </TargetId>
        </ReferenceNode>
        <ReferenceNode>
          <ReferenceTypeId>
            <Identifier>i=37</Identifier>
          </ReferenceTypeId>
          <IsInverse>false</IsInverse>
          <TargetId>
            <Identifier>i=78</Identifier>
          </TargetId>
        </ReferenceNode>
      </References>
      <EventNotifier>0</EventNotifier>
    </Node>
    <Node i:type="ObjectNode">
      <NodeId>
        <Identifier>ns=1;i=5006</Identifier>
      </NodeId>
      <NodeClass>Object_1</NodeClass>
      <BrowseName>
        <NamespaceIndex>1</NamespaceIndex>
        <Name>GlobalVars</Name>
      </BrowseName>
      <DisplayName>
        <Locale></Locale>
        <Text>GlobalVars</Text>
      </DisplayName>
      <Description i:nil="true" />
      <WriteMask>0</WriteMask>
      <UserWriteMask>0</UserWriteMask>
      <References>
        <ReferenceNode>
          <ReferenceTypeId>
            <Identifier>i=47</Identifier>
          </ReferenceTypeId>
          <IsInverse>true</IsInverse>
          <TargetId>
            <Identifier>ns=1;i=1001</Identifier>
          </TargetId>
        </ReferenceNode>
        <ReferenceNode>
          <ReferenceTypeId>
            <Identifier>i=40</Identifier>
          </ReferenceTypeId>
          <IsInverse>false</IsInverse>
          <TargetId>
            <Identifier>ns=2;i=1005</Identifier>
          </TargetId>
        </ReferenceNode>
        <ReferenceNode>
          <ReferenceTypeId>
            <Identifier>i=37</Identifier>
          </ReferenceTypeId>
          <IsInverse>false</IsInverse>
          <TargetId>
            <Identifier>i=78</Identifier>
          </TargetId>
        </ReferenceNode>
      </References>
      <EventNotifier>0</EventNotifier>
    </Node>
    <Node i:type="ObjectNode">
      <NodeId>
        <Identifier>ns=1;i=5007</Identifier>
      </NodeId>
      <NodeClass>Object_1</NodeClass>
      <BrowseName>
        <NamespaceIndex>1</NamespaceIndex>
        <Name>AccessVars</Name>
      </BrowseName>
      <DisplayName>
        <Locale></Locale>
        <Text>AccessVars</Text>
      </DisplayName>
      <Description i:nil="true" />
      <WriteMask>0</WriteMask>
      <UserWriteMask>0</UserWriteMask>
      <References>
        <ReferenceNode>
          <ReferenceTypeId>
            <Identifier>i=47</Identifier>
          </ReferenceTypeId>
          <IsInverse>true</IsInverse>
          <TargetId>
            <Identifier>ns=1;i=1001</Identifier>
          </TargetId>
        </ReferenceNode>
        <ReferenceNode>
          <ReferenceTypeId>
            <Identifier>i=40</Identifier>
          </ReferenceTypeId>
          <IsInverse>false</IsInverse>
          <TargetId>
            <Identifier>ns=2;i=1005</Identifier>
          </TargetId>
        </ReferenceNode>
        <ReferenceNode>
          <ReferenceTypeId>
            <Identifier>i=37</Identifier>
          </ReferenceTypeId>
          <IsInverse>false</IsInverse>
          <TargetId>
            <Identifier>i=78</Identifier>
          </TargetId>
        </ReferenceNode>
      </References>
      <EventNotifier>0</EventNotifier>
    </Node>
    <Node i:type="ObjectNode">
      <NodeId>
        <Identifier>ns=1;i=5008</Identifier>
      </NodeId>
      <NodeClass>Object_1</NodeClass>
      <BrowseName>
        <NamespaceIndex>1</NamespaceIndex>
        <Name>ConfigVars</Name>
      </BrowseName>
      <DisplayName>
        <Locale></Locale>
        <Text>ConfigVars</Text>
      </DisplayName>
      <Description i:nil="true" />
      <WriteMask>0</WriteMask>
      <UserWriteMask>0</UserWriteMask>
      <References>
        <ReferenceNode>
          <ReferenceTypeId>
            <Identifier>i=47</Identifier>
          </ReferenceTypeId>
          <IsInverse>true</IsInverse>
          <TargetId>
            <Identifier>ns=1;i=1001</Identifier>
          </TargetId>
        </ReferenceNode>
        <ReferenceNode>
          <ReferenceTypeId>
            <Identifier>i=40</Identifier>
          </ReferenceTypeId>
          <IsInverse>false</IsInverse>
          <TargetId>
            <Identifier>ns=2;i=1005</Identifier>
          </TargetId>
        </ReferenceNode>
        <ReferenceNode>
          <ReferenceTypeId>
            <Identifier>i=37</Identifier>
          </ReferenceTypeId>
          <IsInverse>false</IsInverse>
          <TargetId>
            <Identifier>i=78</Identifier>
          </TargetId>
        </ReferenceNode>
      </References>
      <EventNotifier>0</EventNotifier>
    </Node>
    <Node i:type="ObjectNode">
      <NodeId>
        <Identifier>ns=1;i=5009</Identifier>
      </NodeId>
      <NodeClass>Object_1</NodeClass>
      <BrowseName>
        <NamespaceIndex>1</NamespaceIndex>
        <Name>Configuration</Name>
      </BrowseName>
      <DisplayName>
        <Locale></Locale>
        <Text>Configuration</Text>
      </DisplayName>
      <Description i:nil="true" />
      <WriteMask>0</WriteMask>
      <UserWriteMask>0</UserWriteMask>
      <References>
        <ReferenceNode>
          <ReferenceTypeId>
            <Identifier>i=47</Identifier>
          </ReferenceTypeId>
          <IsInverse>true</IsInverse>
          <TargetId>
            <Identifier>ns=1;i=1001</Identifier>
          </TargetId>
        </ReferenceNode>
        <ReferenceNode>
          <ReferenceTypeId>
            <Identifier>i=40</Identifier>
          </ReferenceTypeId>
          <IsInverse>false</IsInverse>
          <TargetId>
            <Identifier>ns=2;i=1005</Identifier>
          </TargetId>
        </ReferenceNode>
        <ReferenceNode>
          <ReferenceTypeId>
            <Identifier>i=37</Identifier>
          </ReferenceTypeId>
          <IsInverse>false</IsInverse>
          <TargetId>
            <Identifier>i=78</Identifier>
          </TargetId>
        </ReferenceNode>
      </References>
      <EventNotifier>0</EventNotifier>
    </Node>
    <Node i:type="ObjectNode">
      <NodeId>
        <Identifier>ns=1;i=5010</Identifier>
      </NodeId>
      <NodeClass>Object_1</NodeClass>
      <BrowseName>
        <NamespaceIndex>1</NamespaceIndex>
        <Name>Diagnostic</Name>
      </BrowseName>
      <DisplayName>
        <Locale></Locale>
        <Text>Diagnostic</Text>
      </DisplayName>
      <Description i:nil="true" />
      <WriteMask>0</WriteMask>
      <UserWriteMask>0</UserWriteMask>
      <References>
        <ReferenceNode>
          <ReferenceTypeId>
            <Identifier>i=47</Identifier>
          </ReferenceTypeId>
          <IsInverse>true</IsInverse>
          <TargetId>
            <Identifier>ns=1;i=1001</Identifier>
          </TargetId>
        </ReferenceNode>
        <ReferenceNode>
          <ReferenceTypeId>
            <Identifier>i=40</Identifier>
          </ReferenceTypeId>
          <IsInverse>false</IsInverse>
          <TargetId>
            <Identifier>ns=2;i=1005</Identifier>
          </TargetId>
        </ReferenceNode>
        <ReferenceNode>
          <ReferenceTypeId>
            <Identifier>i=37</Identifier>
          </ReferenceTypeId>
          <IsInverse>false</IsInverse>
          <TargetId>
            <Identifier>i=78</Identifier>
          </TargetId>
        </ReferenceNode>
      </References>
      <EventNotifier>0</EventNotifier>
    </Node>
    <Node i:type="ObjectNode">
      <NodeId>
        <Identifier>ns=1;i=5012</Identifier>
      </NodeId>
      <NodeClass>Object_1</NodeClass>
      <BrowseName>
        <NamespaceIndex>1</NamespaceIndex>
        <Name>MethodSet</Name>
      </BrowseName>
      <DisplayName>
        <Locale></Locale>
        <Text>MethodSet</Text>
      </DisplayName>
      <Description>
        <Locale></Locale>
        <Text>Flat list of Methods</Text>
      </Description>
      <WriteMask>0</WriteMask>
      <UserWriteMask>0</UserWriteMask>
      <References>
        <ReferenceNode>
          <ReferenceTypeId>
            <Identifier>i=47</Identifier>
          </ReferenceTypeId>
          <IsInverse>true</IsInverse>
          <TargetId>
            <Identifier>ns=1;i=1002</Identifier>
          </TargetId>
        </ReferenceNode>
        <ReferenceNode>
          <ReferenceTypeId>
            <Identifier>i=40</Identifier>
          </ReferenceTypeId>
          <IsInverse>false</IsInverse>
          <TargetId>
            <Identifier>i=58</Identifier>
          </TargetId>
        </ReferenceNode>
        <ReferenceNode>
          <ReferenceTypeId>
            <Identifier>i=37</Identifier>
          </ReferenceTypeId>
          <IsInverse>false</IsInverse>
          <TargetId>
            <Identifier>i=80</Identifier>
          </TargetId>
        </ReferenceNode>
        <ReferenceNode>
          <ReferenceTypeId>
            <Identifier>i=47</Identifier>
          </ReferenceTypeId>
          <IsInverse>false</IsInverse>
          <TargetId>
            <Identifier>ns=1;i=7003</Identifier>
          </TargetId>
        </ReferenceNode>
        <ReferenceNode>
          <ReferenceTypeId>
            <Identifier>i=47</Identifier>
          </ReferenceTypeId>
          <IsInverse>false</IsInverse>
          <TargetId>
            <Identifier>ns=1;i=7004</Identifier>
          </TargetId>
        </ReferenceNode>
      </References>
      <EventNotifier>0</EventNotifier>
    </Node>
    <Node i:type="ObjectNode">
      <NodeId>
        <Identifier>ns=1;i=5014</Identifier>
      </NodeId>
      <NodeClass>Object_1</NodeClass>
      <BrowseName>
        <NamespaceIndex>1</NamespaceIndex>
        <Name>Tasks</Name>
      </BrowseName>
      <DisplayName>
        <Locale></Locale>
        <Text>Tasks</Text>
      </DisplayName>
      <Description i:nil="true" />
      <WriteMask>0</WriteMask>
      <UserWriteMask>0</UserWriteMask>
      <References>
        <ReferenceNode>
          <ReferenceTypeId>
            <Identifier>i=47</Identifier>
          </ReferenceTypeId>
          <IsInverse>true</IsInverse>
          <TargetId>
            <Identifier>ns=1;i=1002</Identifier>
          </TargetId>
        </ReferenceNode>
        <ReferenceNode>
          <ReferenceTypeId>
            <Identifier>i=40</Identifier>
          </ReferenceTypeId>
          <IsInverse>false</IsInverse>
          <TargetId>
            <Identifier>ns=2;i=1004</Identifier>
          </TargetId>
        </ReferenceNode>
        <ReferenceNode>
          <ReferenceTypeId>
            <Identifier>i=37</Identifier>
          </ReferenceTypeId>
          <IsInverse>false</IsInverse>
          <TargetId>
            <Identifier>i=78</Identifier>
          </TargetId>
        </ReferenceNode>
        <ReferenceNode>
          <ReferenceTypeId>
            <Identifier>i=47</Identifier>
          </ReferenceTypeId>
          <IsInverse>false</IsInverse>
          <TargetId>
            <Identifier>ns=1;i=5015</Identifier>
          </TargetId>
        </ReferenceNode>
      </References>
      <EventNotifier>0</EventNotifier>
    </Node>
    <Node i:type="ObjectNode">
      <NodeId>
        <Identifier>ns=1;i=5015</Identifier>
      </NodeId>
      <NodeClass>Object_1</NodeClass>
      <BrowseName>
        <NamespaceIndex>2</NamespaceIndex>
        <Name>SupportedTypes</Name>
      </BrowseName>
      <DisplayName>
        <Locale></Locale>
        <Text>SupportedTypes</Text>
      </DisplayName>
      <Description>
        <Locale></Locale>
        <Text>Folder maintaining the set of (sub-types of) BaseObjectTypes that can be instantiated in the ConfigurableComponent</Text>
      </Description>
      <WriteMask>0</WriteMask>
      <UserWriteMask>0</UserWriteMask>
      <References>
        <ReferenceNode>
          <ReferenceTypeId>
            <Identifier>i=47</Identifier>
          </ReferenceTypeId>
          <IsInverse>true</IsInverse>
          <TargetId>
            <Identifier>ns=1;i=5014</Identifier>
          </TargetId>
        </ReferenceNode>
        <ReferenceNode>
          <ReferenceTypeId>
            <Identifier>i=40</Identifier>
          </ReferenceTypeId>
          <IsInverse>false</IsInverse>
          <TargetId>
            <Identifier>i=61</Identifier>
          </TargetId>
        </ReferenceNode>
        <ReferenceNode>
          <ReferenceTypeId>
            <Identifier>i=37</Identifier>
          </ReferenceTypeId>
          <IsInverse>false</IsInverse>
          <TargetId>
            <Identifier>i=78</Identifier>
          </TargetId>
        </ReferenceNode>
      </References>
      <EventNotifier>0</EventNotifier>
    </Node>
    <Node i:type="ObjectNode">
      <NodeId>
        <Identifier>ns=1;i=5016</Identifier>
      </NodeId>
      <NodeClass>Object_1</NodeClass>
      <BrowseName>
        <NamespaceIndex>1</NamespaceIndex>
        <Name>Programs</Name>
      </BrowseName>
      <DisplayName>
        <Locale></Locale>
        <Text>Programs</Text>
      </DisplayName>
      <Description i:nil="true" />
      <WriteMask>0</WriteMask>
      <UserWriteMask>0</UserWriteMask>
      <References>
        <ReferenceNode>
          <ReferenceTypeId>
            <Identifier>i=47</Identifier>
          </ReferenceTypeId>
          <IsInverse>true</IsInverse>
          <TargetId>
            <Identifier>ns=1;i=1002</Identifier>
          </TargetId>
        </ReferenceNode>
        <ReferenceNode>
          <ReferenceTypeId>
            <Identifier>i=40</Identifier>
          </ReferenceTypeId>
          <IsInverse>false</IsInverse>
          <TargetId>
            <Identifier>ns=2;i=1004</Identifier>
          </TargetId>
        </ReferenceNode>
        <ReferenceNode>
          <ReferenceTypeId>
            <Identifier>i=37</Identifier>
          </ReferenceTypeId>
          <IsInverse>false</IsInverse>
          <TargetId>
            <Identifier>i=78</Identifier>
          </TargetId>
        </ReferenceNode>
        <ReferenceNode>
          <ReferenceTypeId>
            <Identifier>i=47</Identifier>
          </ReferenceTypeId>
          <IsInverse>false</IsInverse>
          <TargetId>
            <Identifier>ns=1;i=5017</Identifier>
          </TargetId>
        </ReferenceNode>
      </References>
      <EventNotifier>0</EventNotifier>
    </Node>
    <Node i:type="ObjectNode">
      <NodeId>
        <Identifier>ns=1;i=5017</Identifier>
      </NodeId>
      <NodeClass>Object_1</NodeClass>
      <BrowseName>
        <NamespaceIndex>2</NamespaceIndex>
        <Name>SupportedTypes</Name>
      </BrowseName>
      <DisplayName>
        <Locale></Locale>
        <Text>SupportedTypes</Text>
      </DisplayName>
      <Description>
        <Locale></Locale>
        <Text>Folder maintaining the set of (sub-types of) BaseObjectTypes that can be instantiated in the ConfigurableComponent</Text>
      </Description>
      <WriteMask>0</WriteMask>
      <UserWriteMask>0</UserWriteMask>
      <References>
        <ReferenceNode>
          <ReferenceTypeId>
            <Identifier>i=47</Identifier>
          </ReferenceTypeId>
          <IsInverse>true</IsInverse>
          <TargetId>
            <Identifier>ns=1;i=5016</Identifier>
          </TargetId>
        </ReferenceNode>
        <ReferenceNode>
          <ReferenceTypeId>
            <Identifier>i=40</Identifier>
          </ReferenceTypeId>
          <IsInverse>false</IsInverse>
          <TargetId>
            <Identifier>i=61</Identifier>
          </TargetId>
        </ReferenceNode>
        <ReferenceNode>
          <ReferenceTypeId>
            <Identifier>i=37</Identifier>
          </ReferenceTypeId>
          <IsInverse>false</IsInverse>
          <TargetId>
            <Identifier>i=78</Identifier>
          </TargetId>
        </ReferenceNode>
      </References>
      <EventNotifier>0</EventNotifier>
    </Node>
    <Node i:type="ObjectNode">
      <NodeId>
        <Identifier>ns=1;i=5018</Identifier>
      </NodeId>
      <NodeClass>Object_1</NodeClass>
      <BrowseName>
        <NamespaceIndex>1</NamespaceIndex>
        <Name>GlobalVars</Name>
      </BrowseName>
      <DisplayName>
        <Locale></Locale>
        <Text>GlobalVars</Text>
      </DisplayName>
      <Description i:nil="true" />
      <WriteMask>0</WriteMask>
      <UserWriteMask>0</UserWriteMask>
      <References>
        <ReferenceNode>
          <ReferenceTypeId>
            <Identifier>i=47</Identifier>
          </ReferenceTypeId>
          <IsInverse>true</IsInverse>
          <TargetId>
            <Identifier>ns=1;i=1002</Identifier>
          </TargetId>
        </ReferenceNode>
        <ReferenceNode>
          <ReferenceTypeId>
            <Identifier>i=40</Identifier>
          </ReferenceTypeId>
          <IsInverse>false</IsInverse>
          <TargetId>
            <Identifier>ns=2;i=1005</Identifier>
          </TargetId>
        </ReferenceNode>
        <ReferenceNode>
          <ReferenceTypeId>
            <Identifier>i=37</Identifier>
          </ReferenceTypeId>
          <IsInverse>false</IsInverse>
          <TargetId>
            <Identifier>i=80</Identifier>
          </TargetId>
        </ReferenceNode>
      </References>
      <EventNotifier>0</EventNotifier>
    </Node>
    <Node i:type="ObjectNode">
      <NodeId>
        <Identifier>ns=1;i=5019</Identifier>
      </NodeId>
      <NodeClass>Object_1</NodeClass>
      <BrowseName>
        <NamespaceIndex>1</NamespaceIndex>
        <Name>Configuration</Name>
      </BrowseName>
      <DisplayName>
        <Locale></Locale>
        <Text>Configuration</Text>
      </DisplayName>
      <Description i:nil="true" />
      <WriteMask>0</WriteMask>
      <UserWriteMask>0</UserWriteMask>
      <References>
        <ReferenceNode>
          <ReferenceTypeId>
            <Identifier>i=47</Identifier>
          </ReferenceTypeId>
          <IsInverse>true</IsInverse>
          <TargetId>
            <Identifier>ns=1;i=1002</Identifier>
          </TargetId>
        </ReferenceNode>
        <ReferenceNode>
          <ReferenceTypeId>
            <Identifier>i=40</Identifier>
          </ReferenceTypeId>
          <IsInverse>false</IsInverse>
          <TargetId>
            <Identifier>ns=2;i=1005</Identifier>
          </TargetId>
        </ReferenceNode>
        <ReferenceNode>
          <ReferenceTypeId>
            <Identifier>i=37</Identifier>
          </ReferenceTypeId>
          <IsInverse>false</IsInverse>
          <TargetId>
            <Identifier>i=80</Identifier>
          </TargetId>
        </ReferenceNode>
      </References>
      <EventNotifier>0</EventNotifier>
    </Node>
    <Node i:type="ObjectNode">
      <NodeId>
        <Identifier>ns=1;i=5020</Identifier>
      </NodeId>
      <NodeClass>Object_1</NodeClass>
      <BrowseName>
        <NamespaceIndex>1</NamespaceIndex>
        <Name>Diagnostic</Name>
      </BrowseName>
      <DisplayName>
        <Locale></Locale>
        <Text>Diagnostic</Text>
      </DisplayName>
      <Description i:nil="true" />
      <WriteMask>0</WriteMask>
      <UserWriteMask>0</UserWriteMask>
      <References>
        <ReferenceNode>
          <ReferenceTypeId>
            <Identifier>i=47</Identifier>
          </ReferenceTypeId>
          <IsInverse>true</IsInverse>
          <TargetId>
            <Identifier>ns=1;i=1002</Identifier>
          </TargetId>
        </ReferenceNode>
        <ReferenceNode>
          <ReferenceTypeId>
            <Identifier>i=40</Identifier>
          </ReferenceTypeId>
          <IsInverse>false</IsInverse>
          <TargetId>
            <Identifier>ns=2;i=1005</Identifier>
          </TargetId>
        </ReferenceNode>
        <ReferenceNode>
          <ReferenceTypeId>
            <Identifier>i=37</Identifier>
          </ReferenceTypeId>
          <IsInverse>false</IsInverse>
          <TargetId>
            <Identifier>i=80</Identifier>
          </TargetId>
        </ReferenceNode>
      </References>
      <EventNotifier>0</EventNotifier>
    </Node>
    <Node i:type="VariableNode">
      <NodeId>
        <Identifier>ns=1;i=6001</Identifier>
      </NodeId>
      <NodeClass>Variable_2</NodeClass>
      <BrowseName>
        <NamespaceIndex>1</NamespaceIndex>
        <Name>Body</Name>
      </BrowseName>
      <DisplayName>
        <Locale></Locale>
        <Text>Body</Text>
      </DisplayName>
      <Description i:nil="true" />
      <WriteMask>0</WriteMask>
      <UserWriteMask>0</UserWriteMask>
      <References>
        <ReferenceNode>
          <ReferenceTypeId>
            <Identifier>i=47</Identifier>
          </ReferenceTypeId>
          <IsInverse>true</IsInverse>
          <TargetId>
            <Identifier>ns=1;i=1003</Identifier>
          </TargetId>
        </ReferenceNode>
        <ReferenceNode>
          <ReferenceTypeId>
            <Identifier>i=40</Identifier>
          </ReferenceTypeId>
          <IsInverse>false</IsInverse>
          <TargetId>
            <Identifier>i=63</Identifier>
          </TargetId>
        </ReferenceNode>
        <ReferenceNode>
          <ReferenceTypeId>
            <Identifier>i=37</Identifier>
          </ReferenceTypeId>
          <IsInverse>false</IsInverse>
          <TargetId>
            <Identifier>i=80</Identifier>
          </TargetId>
        </ReferenceNode>
      </References>
      <Value>
        <Value>
          <Null xmlns="http://opcfoundation.org/UA/2008/02/Types.xsd" />
        </Value>
      </Value>
      <DataType>
        <Identifier>i=16</Identifier>
      </DataType>
      <ValueRank>-1</ValueRank>
      <ArrayDimensions />
      <AccessLevel>1</AccessLevel>
      <UserAccessLevel>1</UserAccessLevel>
      <MinimumSamplingInterval>0</MinimumSamplingInterval>
      <Historizing>false</Historizing>
    </Node>
    <Node i:type="VariableNode">
      <NodeId>
        <Identifier>ns=1;i=6002</Identifier>
      </NodeId>
      <NodeClass>Variable_2</NodeClass>
      <BrowseName>
        <NamespaceIndex>1</NamespaceIndex>
        <Name>Program</Name>
      </BrowseName>
      <DisplayName>
        <Locale></Locale>
        <Text>Program</Text>
      </DisplayName>
      <Description i:nil="true" />
      <WriteMask>0</WriteMask>
      <UserWriteMask>0</UserWriteMask>
      <References>
        <ReferenceNode>
          <ReferenceTypeId>
            <Identifier>i=47</Identifier>
          </ReferenceTypeId>
          <IsInverse>true</IsInverse>
          <TargetId>
            <Identifier>ns=1;i=1004</Identifier>
          </TargetId>
        </ReferenceNode>
        <ReferenceNode>
          <ReferenceTypeId>
            <Identifier>i=40</Identifier>
          </ReferenceTypeId>
          <IsInverse>false</IsInverse>
          <TargetId>
            <Identifier>i=63</Identifier>
          </TargetId>
        </ReferenceNode>
        <ReferenceNode>
          <ReferenceTypeId>
            <Identifier>i=37</Identifier>
          </ReferenceTypeId>
          <IsInverse>false</IsInverse>
          <TargetId>
            <Identifier>i=80</Identifier>
          </TargetId>
        </ReferenceNode>
      </References>
      <Value>
        <Value>
          <Null xmlns="http://opcfoundation.org/UA/2008/02/Types.xsd" />
        </Value>
      </Value>
      <DataType>
        <Identifier>i=22</Identifier>
      </DataType>
      <ValueRank>-1</ValueRank>
      <ArrayDimensions />
      <AccessLevel>1</AccessLevel>
      <UserAccessLevel>1</UserAccessLevel>
      <MinimumSamplingInterval>0</MinimumSamplingInterval>
      <Historizing>false</Historizing>
    </Node>
    <Node i:type="VariableNode">
      <NodeId>
        <Identifier>ns=1;i=6003</Identifier>
      </NodeId>
      <NodeClass>Variable_2</NodeClass>
      <BrowseName>
        <NamespaceIndex>1</NamespaceIndex>
        <Name>FunctionBlock</Name>
      </BrowseName>
      <DisplayName>
        <Locale></Locale>
        <Text>FunctionBlock</Text>
      </DisplayName>
      <Description i:nil="true" />
      <WriteMask>0</WriteMask>
      <UserWriteMask>0</UserWriteMask>
      <References>
        <ReferenceNode>
          <ReferenceTypeId>
            <Identifier>i=47</Identifier>
          </ReferenceTypeId>
          <IsInverse>true</IsInverse>
          <TargetId>
            <Identifier>ns=1;i=1005</Identifier>
          </TargetId>
        </ReferenceNode>
        <ReferenceNode>
          <ReferenceTypeId>
            <Identifier>i=40</Identifier>
          </ReferenceTypeId>
          <IsInverse>false</IsInverse>
          <TargetId>
            <Identifier>i=63</Identifier>
          </TargetId>
        </ReferenceNode>
        <ReferenceNode>
          <ReferenceTypeId>
            <Identifier>i=37</Identifier>
          </ReferenceTypeId>
          <IsInverse>false</IsInverse>
          <TargetId>
            <Identifier>i=80</Identifier>
          </TargetId>
        </ReferenceNode>
      </References>
      <Value>
        <Value>
          <Null xmlns="http://opcfoundation.org/UA/2008/02/Types.xsd" />
        </Value>
      </Value>
      <DataType>
        <Identifier>i=24</Identifier>
      </DataType>
      <ValueRank>-1</ValueRank>
      <ArrayDimensions />
      <AccessLevel>1</AccessLevel>
      <UserAccessLevel>1</UserAccessLevel>
      <MinimumSamplingInterval>0</MinimumSamplingInterval>
      <Historizing>false</Historizing>
    </Node>
    <Node i:type="VariableNode">
      <NodeId>
        <Identifier>ns=1;i=6004</Identifier>
      </NodeId>
      <NodeClass>Variable_2</NodeClass>
      <BrowseName>
        <NamespaceIndex>1</NamespaceIndex>
        <Name>Priority</Name>
      </BrowseName>
      <DisplayName>
        <Locale></Locale>
        <Text>Priority</Text>
      </DisplayName>
      <Description i:nil="true" />
      <WriteMask>0</WriteMask>
      <UserWriteMask>0</UserWriteMask>
      <References>
        <ReferenceNode>
          <ReferenceTypeId>
            <Identifier>i=46</Identifier>
          </ReferenceTypeId>
          <IsInverse>true</IsInverse>
          <TargetId>
            <Identifier>ns=1;i=1006</Identifier>
          </TargetId>
        </ReferenceNode>
        <ReferenceNode>
          <ReferenceTypeId>
            <Identifier>i=40</Identifier>
          </ReferenceTypeId>
          <IsInverse>false</IsInverse>
          <TargetId>
            <Identifier>i=68</Identifier>
          </TargetId>
        </ReferenceNode>
        <ReferenceNode>
          <ReferenceTypeId>
            <Identifier>i=37</Identifier>
          </ReferenceTypeId>
          <IsInverse>false</IsInverse>
          <TargetId>
            <Identifier>i=78</Identifier>
          </TargetId>
        </ReferenceNode>
      </References>
      <Value>
        <Value>
          <UInt32 xmlns="http://opcfoundation.org/UA/2008/02/Types.xsd">0</UInt32>
        </Value>
      </Value>
      <DataType>
        <Identifier>i=7</Identifier>
      </DataType>
      <ValueRank>-1</ValueRank>
      <ArrayDimensions />
      <AccessLevel>1</AccessLevel>
      <UserAccessLevel>1</UserAccessLevel>
      <MinimumSamplingInterval>0</MinimumSamplingInterval>
      <Historizing>false</Historizing>
    </Node>
    <Node i:type="VariableNode">
      <NodeId>
        <Identifier>ns=1;i=6005</Identifier>
      </NodeId>
      <NodeClass>Variable_2</NodeClass>
      <BrowseName>
        <NamespaceIndex>1</NamespaceIndex>
        <Name>Interval</Name>
      </BrowseName>
      <DisplayName>
        <Locale></Locale>
        <Text>Interval</Text>
      </DisplayName>
      <Description i:nil="true" />
      <WriteMask>0</WriteMask>
      <UserWriteMask>0</UserWriteMask>
      <References>
        <ReferenceNode>
          <ReferenceTypeId>
            <Identifier>i=46</Identifier>
          </ReferenceTypeId>
          <IsInverse>true</IsInverse>
          <TargetId>
            <Identifier>ns=1;i=1006</Identifier>
          </TargetId>
        </ReferenceNode>
        <ReferenceNode>
          <ReferenceTypeId>
            <Identifier>i=40</Identifier>
          </ReferenceTypeId>
          <IsInverse>false</IsInverse>
          <TargetId>
            <Identifier>i=68</Identifier>
          </TargetId>
        </ReferenceNode>
        <ReferenceNode>
          <ReferenceTypeId>
            <Identifier>i=37</Identifier>
          </ReferenceTypeId>
          <IsInverse>false</IsInverse>
          <TargetId>
            <Identifier>i=80</Identifier>
          </TargetId>
        </ReferenceNode>
      </References>
      <Value>
        <Value>
          <Null xmlns="http://opcfoundation.org/UA/2008/02/Types.xsd" />
        </Value>
      </Value>
      <DataType>
        <Identifier>i=12</Identifier>
      </DataType>
      <ValueRank>-1</ValueRank>
      <ArrayDimensions />
      <AccessLevel>1</AccessLevel>
      <UserAccessLevel>1</UserAccessLevel>
      <MinimumSamplingInterval>0</MinimumSamplingInterval>
      <Historizing>false</Historizing>
    </Node>
    <Node i:type="VariableNode">
      <NodeId>
        <Identifier>ns=1;i=6006</Identifier>
      </NodeId>
      <NodeClass>Variable_2</NodeClass>
      <BrowseName>
        <NamespaceIndex>1</NamespaceIndex>
        <Name>Single</Name>
      </BrowseName>
      <DisplayName>
        <Locale></Locale>
        <Text>Single</Text>
      </DisplayName>
      <Description i:nil="true" />
      <WriteMask>0</WriteMask>
      <UserWriteMask>0</UserWriteMask>
      <References>
        <ReferenceNode>
          <ReferenceTypeId>
            <Identifier>i=46</Identifier>
          </ReferenceTypeId>
          <IsInverse>true</IsInverse>
          <TargetId>
            <Identifier>ns=1;i=1006</Identifier>
          </TargetId>
        </ReferenceNode>
        <ReferenceNode>
          <ReferenceTypeId>
            <Identifier>i=40</Identifier>
          </ReferenceTypeId>
          <IsInverse>false</IsInverse>
          <TargetId>
            <Identifier>i=68</Identifier>
          </TargetId>
        </ReferenceNode>
        <ReferenceNode>
          <ReferenceTypeId>
            <Identifier>i=37</Identifier>
          </ReferenceTypeId>
          <IsInverse>false</IsInverse>
          <TargetId>
            <Identifier>i=80</Identifier>
          </TargetId>
        </ReferenceNode>
      </References>
      <Value>
        <Value>
          <Null xmlns="http://opcfoundation.org/UA/2008/02/Types.xsd" />
        </Value>
      </Value>
      <DataType>
        <Identifier>i=12</Identifier>
      </DataType>
      <ValueRank>-1</ValueRank>
      <ArrayDimensions />
      <AccessLevel>1</AccessLevel>
      <UserAccessLevel>1</UserAccessLevel>
      <MinimumSamplingInterval>0</MinimumSamplingInterval>
      <Historizing>false</Historizing>
    </Node>
    <Node i:type="MethodNode">
      <NodeId>
        <Identifier>ns=1;i=7001</Identifier>
      </NodeId>
      <NodeClass>Method_4</NodeClass>
      <BrowseName>
        <NamespaceIndex>1</NamespaceIndex>
        <Name>Start</Name>
      </BrowseName>
      <DisplayName>
        <Locale></Locale>
        <Text>Start</Text>
      </DisplayName>
      <Description i:nil="true" />
      <WriteMask>0</WriteMask>
      <UserWriteMask>0</UserWriteMask>
      <References>
        <ReferenceNode>
          <ReferenceTypeId>
            <Identifier>i=47</Identifier>
          </ReferenceTypeId>
          <IsInverse>true</IsInverse>
          <TargetId>
            <Identifier>ns=1;i=5002</Identifier>
          </TargetId>
        </ReferenceNode>
        <ReferenceNode>
          <ReferenceTypeId>
            <Identifier>i=40</Identifier>
          </ReferenceTypeId>
          <IsInverse>false</IsInverse>
          <TargetId>
            <Identifier>ns=1;i=7001</Identifier>
          </TargetId>
        </ReferenceNode>
        <ReferenceNode>
          <ReferenceTypeId>
            <Identifier>i=37</Identifier>
          </ReferenceTypeId>
          <IsInverse>false</IsInverse>
          <TargetId>
            <Identifier>i=80</Identifier>
          </TargetId>
        </ReferenceNode>
      </References>
      <Executable>true</Executable>
      <UserExecutable>true</UserExecutable>
    </Node>
    <Node i:type="MethodNode">
      <NodeId>
        <Identifier>ns=1;i=7002</Identifier>
      </NodeId>
      <NodeClass>Method_4</NodeClass>
      <BrowseName>
        <NamespaceIndex>1</NamespaceIndex>
        <Name>Stop</Name>
      </BrowseName>
      <DisplayName>
        <Locale></Locale>
        <Text>Stop</Text>
      </DisplayName>
      <Description i:nil="true" />
      <WriteMask>0</WriteMask>
      <UserWriteMask>0</UserWriteMask>
      <References>
        <ReferenceNode>
          <ReferenceTypeId>
            <Identifier>i=47</Identifier>
          </ReferenceTypeId>
          <IsInverse>true</IsInverse>
          <TargetId>
            <Identifier>ns=1;i=5002</Identifier>
          </TargetId>
        </ReferenceNode>
        <ReferenceNode>
          <ReferenceTypeId>
            <Identifier>i=40</Identifier>
          </ReferenceTypeId>
          <IsInverse>false</IsInverse>
          <TargetId>
            <Identifier>ns=1;i=7002</Identifier>
          </TargetId>
        </ReferenceNode>
        <ReferenceNode>
          <ReferenceTypeId>
            <Identifier>i=37</Identifier>
          </ReferenceTypeId>
          <IsInverse>false</IsInverse>
          <TargetId>
            <Identifier>i=80</Identifier>
          </TargetId>
        </ReferenceNode>
      </References>
      <Executable>true</Executable>
      <UserExecutable>true</UserExecutable>
    </Node>
    <Node i:type="MethodNode">
      <NodeId>
        <Identifier>ns=1;i=7003</Identifier>
      </NodeId>
      <NodeClass>Method_4</NodeClass>
      <BrowseName>
        <NamespaceIndex>1</NamespaceIndex>
        <Name>Start</Name>
      </BrowseName>
      <DisplayName>
        <Locale></Locale>
        <Text>Start</Text>
      </DisplayName>
      <Description i:nil="true" />
      <WriteMask>0</WriteMask>
      <UserWriteMask>0</UserWriteMask>
      <References>
        <ReferenceNode>
          <ReferenceTypeId>
            <Identifier>i=47</Identifier>
          </ReferenceTypeId>
          <IsInverse>true</IsInverse>
          <TargetId>
            <Identifier>ns=1;i=5012</Identifier>
          </TargetId>
        </ReferenceNode>
        <ReferenceNode>
          <ReferenceTypeId>
            <Identifier>i=40</Identifier>
          </ReferenceTypeId>
          <IsInverse>false</IsInverse>
          <TargetId>
            <Identifier>ns=1;i=7003</Identifier>
          </TargetId>
        </ReferenceNode>
        <ReferenceNode>
          <ReferenceTypeId>
            <Identifier>i=37</Identifier>
          </ReferenceTypeId>
          <IsInverse>false</IsInverse>
          <TargetId>
            <Identifier>i=80</Identifier>
          </TargetId>
        </ReferenceNode>
      </References>
      <Executable>true</Executable>
      <UserExecutable>true</UserExecutable>
    </Node>
    <Node i:type="MethodNode">
      <NodeId>
        <Identifier>ns=1;i=7004</Identifier>
      </NodeId>
      <NodeClass>Method_4</NodeClass>
      <BrowseName>
        <NamespaceIndex>1</NamespaceIndex>
        <Name>Stop</Name>
      </BrowseName>
      <DisplayName>
        <Locale></Locale>
        <Text>Stop</Text>
      </DisplayName>
      <Description i:nil="true" />
      <WriteMask>0</WriteMask>
      <UserWriteMask>0</UserWriteMask>
      <References>
        <ReferenceNode>
          <ReferenceTypeId>
            <Identifier>i=47</Identifier>
          </ReferenceTypeId>
          <IsInverse>true</IsInverse>
          <TargetId>
            <Identifier>ns=1;i=5012</Identifier>
          </TargetId>
        </ReferenceNode>
        <ReferenceNode>
          <ReferenceTypeId>
            <Identifier>i=40</Identifier>
          </ReferenceTypeId>
          <IsInverse>false</IsInverse>
          <TargetId>
            <Identifier>ns=1;i=7004</Identifier>
          </TargetId>
        </ReferenceNode>
        <ReferenceNode>
          <ReferenceTypeId>
            <Identifier>i=37</Identifier>
          </ReferenceTypeId>
          <IsInverse>false</IsInverse>
          <TargetId>
            <Identifier>i=80</Identifier>
          </TargetId>
        </ReferenceNode>
      </References>
      <Executable>true</Executable>
      <UserExecutable>true</UserExecutable>
    </Node>
  </Nodes>
</NodeSet>